odoo10_addon_account_analytic_distribution_required-10.0.1.0.0-py2.7-nspkg.pth
odoo/addons/account_analytic_distribution_required/README.rst
odoo/addons/account_analytic_distribution_required/__init__.py
odoo/addons/account_analytic_distribution_required/__manifest__.py
odoo/addons/account_analytic_distribution_required/models/__init__.py
odoo/addons/account_analytic_distribution_required/models/account.py
odoo/addons/account_analytic_distribution_required/tests/__init__.py
odoo/addons/account_analytic_distribution_required/tests/test_account_analytic_plan_required.py
odoo10_addon_account_analytic_distribution_required-10.0.1.0.0.dist-info/DESCRIPTION.rst
odoo10_addon_account_analytic_distribution_required-10.0.1.0.0.dist-info/METADATA
odoo10_addon_account_analytic_distribution_required-10.0.1.0.0.dist-info/RECORD
odoo10_addon_account_analytic_distribution_required-10.0.1.0.0.dist-info/WHEEL
odoo10_addon_account_analytic_distribution_required-10.0.1.0.0.dist-info/metadata.json
odoo10_addon_account_analytic_distribution_required-10.0.1.0.0.dist-info/namespace_packages.txt
odoo10_addon_account_analytic_distribution_required-10.0.1.0.0.dist-info/top_level.txt
