Metadata-Version: 2.0
Name: odoo10-addon-account-analytic-distribution-required
Version: 10.0.1.0.0
Summary: Account Analytic Distribution Required
Home-page: http://www.acsone.eu/
Author: ACSONE SA/NV, Tecnativa, Odoo Community Association (OCA)
Author-email: support@odoo-community.org
License: AGPL-3
Platform: UNKNOWN
Classifier: Programming Language :: Python :: 2.7
Classifier: Framework :: Odoo
Classifier: License :: OSI Approved :: GNU Affero General Public License v3
Requires-Dist: odoo (<10.1dev,>=10.0)
Requires-Dist: odoo10-addon-account-analytic-distribution
Requires-Dist: odoo10-addon-account-analytic-required
